Metadata-Version: 1.0
Name: collatzconj
Version: 0.0.3
Summary: collatz conjecture calculation tool
Home-page: UNKNOWN
Author: UNKNOWN
Author-email: UNKNOWN
License: UNKNOWN
Platform: UNKNOWN
